next_composer_vault/__init__.py
next_composer_vault/backend.py
next_composer_vault/client.py
next_composer_vault-0.1.0.dist-info/WHEEL
next_composer_vault-0.1.0.dist-info/METADATA
next_composer_vault-0.1.0.dist-info/RECORD
