Metadata-Version: 2.1
Name: next-composer-vault
Version: 0.1.0
Summary: 
Author: Victor Tsetsulin
Author-email: victor.tsetsulin@nexttrucking.com
Requires-Python: >=3.8,<4.0
Classifier: Programming Language :: Python :: 3
Classifier: Programming Language :: Python :: 3.8
Classifier: Programming Language :: Python :: 3.9
Classifier: Programming Language :: Python :: 3.10
Classifier: Programming Language :: Python :: 3.11
Requires-Dist: hvac (==0.11.2)
